rchf/__init__.py
rchf/demo.py
rchf-1.0.3.dist-info/licenses/LICENSE
rchf-1.0.3.dist-info/METADATA
rchf-1.0.3.dist-info/WHEEL
rchf-1.0.3.dist-info/entry_points.txt
rchf-1.0.3.dist-info/top_level.txt
rchf-1.0.3.dist-info/RECORD
