Metadata-Version: 2.4
Name: rchf
Version: 1.0.3
Summary: Custom Rich Help Formatter - A beautifully styled argparse formatter with rich formatting and multi-config support
Home-page: https://github.com/cumulus13/rchf
Author: Hadi Cahyadi
Author-email: Hadi Cahyadi <cumulus13@gmail.com>
License: MIT
Project-URL: Homepage, https://github.com/cumulus13/rchf
Project-URL: Repository, https://github.com/cumulus13/rchf
Project-URL: BugTracker, https://github.com/cumulus13/rchf/issues
Keywords: argparse,rich,formatter,cli,help,terminal,stylish
Classifier: Development Status :: 4 - Beta
Classifier: Intended Audience :: Developers
Classifier: Operating System :: OS Independent
Classifier: Programming Language :: Python :: 3
Classifier: Programming Language :: Python :: 3.8
Classifier: Programming Language :: Python :: 3.9
Classifier: Programming Language :: Python :: 3.10
Classifier: Programming Language :: Python :: 3.11
Classifier: Programming Language :: Python :: 3.12
Classifier: Topic :: Software Development :: Libraries :: Python Modules
Classifier: Topic :: Software Development :: User Interfaces
Classifier: Topic :: Utilities
Requires-Python: >=3.8
License-File: LICENSE
Requires-Dist: rich>=13.0.0
Requires-Dist: rich-argparse>=1.0.0
Requires-Dist: envdot>=0.1.0
Provides-Extra: dev
Requires-Dist: pytest>=7.0.0; extra == "dev"
Requires-Dist: pytest-cov>=4.0.0; extra == "dev"
Requires-Dist: black>=23.0.0; extra == "dev"
Requires-Dist: isort>=5.12.0; extra == "dev"
Requires-Dist: mypy>=1.0.0; extra == "dev"
Requires-Dist: ruff>=0.1.0; extra == "dev"
Dynamic: author
Dynamic: home-page
Dynamic: license-file
Dynamic: requires-python
